README.md
setup.cfg
setup.py
distributions/Binomialdistribution.py
distributions/Gaussiandistribution.py
distributions/Generaldistribution.py
distributions/__init__.py
minewine_binomial.egg-info/PKG-INFO
minewine_binomial.egg-info/SOURCES.txt
minewine_binomial.egg-info/dependency_links.txt
minewine_binomial.egg-info/not-zip-safe
minewine_binomial.egg-info/top_level.txt